flask_datadog/__init__.py
flask_datadog/monitor/__init__.py
flask_datadog/monitor/route_tagger.py
flask_datadog_monitor-0.0.7.dist-info/LICENSE.txt
flask_datadog_monitor-0.0.7.dist-info/METADATA
flask_datadog_monitor-0.0.7.dist-info/WHEEL
flask_datadog_monitor-0.0.7.dist-info/entry_points.txt
flask_datadog_monitor-0.0.7.dist-info/top_level.txt
flask_datadog_monitor-0.0.7.dist-info/RECORD
